Workbook

Sheet 1. Catálogo
A1: CATÁLOGO DE PRODUCTOS Y SERVICIOS
A3: Código SKU | B3: Nombre Producto | C3: Categoría | D3: Precio Base | E3: Costo Material | F3: Costo Mano Obra | G3: Costo Total | H3: Margen $ | I3: Margen % | J3: Tiempo Prod. (días)
A4: TS-BL-OS | B4: T-shirt Blanco Oversize | C4: Camisetas | D4: 2000 | E4: 400 | F4: 300 | G4: =E4+F4 -> 700 | H4: =D4-G4 -> 1300 | I4: =H4/D4 -> 0.65 | J4: 7
A5: TS-NEG-ST | B5: T-shirt Negro Standard | C5: Camisetas | D5: 2000 | E5: 350 | F5: 300 | G5: =E5+F5 -> 650 | H5: =D5-G5 -> 1350 | I5: =H5/D5 -> 0.675 | J5: 7
A6: HD-NEG-ST | B6: Hoodie Negro Standard | C6: Hoodies | D6: 2700 | E6: 800 | F6: 500 | G6: =E6+F6 -> 1300 | H6: =D6-G6 -> 1400 | I6: =H6/D6 -> 0.51851852 | J6: 10
A7: HD-BL-ST | B7: Hoodie Blanco Standard | C7: Hoodies | D7: 2700 | E7: 800 | F7: 500 | G7: =E7+F7 -> 1300 | H7: =D7-G7 -> 1400 | I7: =H7/D7 -> 0.51851852 | J7: 10
A8: ABR-NEG | B8: Abrigo Negro | C8: Abrigos | D8: 2400 | E8: 700 | F8: 450 | G8: =E8+F8 -> 1150 | H8: =D8-G8 -> 1250 | I8: =H8/D8 -> 0.52083333 | J8: 12
A9: TS-CUST | B9: T-shirt Personalizado | C9: Camisetas | D9: 2200 | E9: 400 | F9: 400 | G9: =E9+F9 -> 800 | H9: =D9-G9 -> 1400 | I9: =H9/D9 -> 0.63636364 | J9: 8
A12: SERVICIOS DE PERSONALIZACIÓN
A13: Código | B13: Tipo Personalización | C13: Precio | D13: Tiempo Adicional (días) | E13: Descripción | F13: Activo
A14: BORD-FRNT | B14: Bordado Frontal | C14: 150 | D14: 1 | E14: Bordado simple en frente | F14: Sí
A15: BORD-BACK | B15: Bordado Espalda | C15: 150 | D15: 1 | E15: Bordado simple en espalda | F15: Sí
A16: BORD-DBL | B16: Bordado Doble | C16: 250 | D16: 2 | E16: Bordado frente y espalda | F16: Sí
A17: PRINT-FRNT | B17: Estampado Frontal | C17: 100 | D17: 0 | E17: Estampado en frente | F17: Sí
A18: EMBROID-LUX | B18: Bordado Lujo | C18: 500 | D18: 3 | E18: Bordado complejo multicolor | F18: Sí

Sheet 2. Pedidos
A1: REGISTRO DE PEDIDOS
A3: ID | B3: Fecha Pago | C3: Fecha Compromiso | D3: Fecha Entrega Real | E3: Días Prod. | F3: Días Retraso | G3: SKU Producto | H3: Producto | I3: Talla | J3: Personalización | K3: Costo Person. | L3: Cliente | M3: Teléfono | N3: Email | O3: Dirección | P3: Canal | Q3: Precio Producto | R3: Precio Person. | S3: Precio Envío | T3: Precio Total | U3: Costo Total | V3: Ganancia | W3: Banco | X3: Estatus Pago | Y3: Estatus Producción
A4: P0001 | B4: 22/01/2026 | C4: 07/02/2026 | E4: =C4-B4 -> 16 | F4: =IF(D4="",IF(TODAY()>C4,TODAY()-C4,0),IF(D4>C4,D4-C4,0)) -> 0 | G4: TS-BL-OS | H4: T-shirt blanco Oversize | I4: L | J4: Dos bordados en frente y uno en la espalda | K4: 400 | L4: Ana | M4: WS | O4: Vimenpaq | P4: WhatsApp | Q4: 2000 | R4: 400 | S4: 750 | T4: =Q4+R4+S4 -> 3150 | U4: =VLOOKUP(G4,'1. Catálogo'!$A$4:$G$9,7,FALSE)+K4+S4 -> 1850 | V4: =T4-U4 -> 1300 | W4: Popular | X4: Recibido | Y4: En Producción
A5: P0002 | B5: 15/01/2026 | C5: 02/02/2026 | E5: =C5-B5 -> 18 | F5: =IF(D5="",IF(TODAY()>C5,TODAY()-C5,0),IF(D5>C5,D5-C5,0)) -> 0 | G5: HD-NEG-ST | H5: Hoodie negro | I5: M | J5: Frente bordado | K5: 150 | L5: Nahomy Rousmery Guerrero | M5: WS | O5: Vimenpaq Villa Mella | P5: WhatsApp | Q5: 2700 | R5: 0 | S5: 0 | T5: =Q5+R5+S5 -> 2700 | U5: =VLOOKUP(G5,'1. Catálogo'!$A$4:$G$9,7,FALSE)+K5+S5 -> 1450 | V5: =T5-U5 -> 1250 | W5: Popular | X5: Recibido | Y5: En Producción
A6: P0003 | B6: 02/02/2026 | C6: 16/02/2026 | E6: =C6-B6 -> 14 | F6: =IF(D6="",IF(TODAY()>C6,TODAY()-C6,0),IF(D6>C6,D6-C6,0)) -> 0 | G6: TS-NEG-ST | H6: T-shirt negro | I6: L | J6: Frente bordado | K6: 150 | L6: Arlin Tomas | M6: WS | O6: Vimenpaq San Pedro | P6: WhatsApp | Q6: 2000 | R6: 0 | S6: 0 | T6: =Q6+R6+S6 -> 2000 | U6: =VLOOKUP(G6,'1. Catálogo'!$A$4:$G$9,7,FALSE)+K6+S6 -> 800 | V6: =T6-U6 -> 1200 | W6: Popular | X6: Recibido | Y6: En Producción
A7: P0004 | B7: 30/01/2026 | C7: 14/02/2026 | E7: =C7-B7 -> 15 | F7: =IF(D7="",IF(TODAY()>C7,TODAY()-C7,0),IF(D7>C7,D7-C7,0)) -> 0 | G7: TS-NEG-ST | H7: T-shirt negro | I7: M | J7: Frente bordado | K7: 150 | L7: Camila Joselin | M7: WS | O7: Pendiente | P7: WhatsApp | Q7: 2000 | R7: 0 | S7: 0 | T7: =Q7+R7+S7 -> 2000 | U7: =VLOOKUP(G7,'1. Catálogo'!$A$4:$G$9,7,FALSE)+K7+S7 -> 800 | V7: =T7-U7 -> 1200 | W7: Banreservas | X7: Recibido | Y7: Bloqueado - Sin Dirección
A8: P0005 | B8: 27/01/2026 | C8: 09/02/2026 | E8: =C8-B8 -> 13 | F8: =IF(D8="",IF(TODAY()>C8,TODAY()-C8,0),IF(D8>C8,D8-C8,0)) -> 0 | G8: HD-NEG-ST | H8: Hoodie negro | I8: M | J8: Un bordado en frente y uno espalda | K8: 250 | L8: Alessia Previtali | M8: WS | O8: Vimenpaq Bayahibe | P8: WhatsApp | Q8: 2700 | R8: 250 | S8: 750 | T8: =Q8+R8+S8 -> 3700 | U8: =VLOOKUP(G8,'1. Catálogo'!$A$4:$G$9,7,FALSE)+K8+S8 -> 2300 | V8: =T8-U8 -> 1400 | W8: Banreservas | X8: Recibido | Y8: En Producción
A9: P0006 | B9: 19/01/2026 | C9: 03/02/2026 | E9: =C9-B9 -> 15 | F9: =IF(D9="",IF(TODAY()>C9,TODAY()-C9,0),IF(D9>C9,D9-C9,0)) -> 0 | G9: TS-NEG-ST | H9: T-shirt negro | I9: L | J9: Frente bordado | K9: 150 | L9: Laiza Cesarina De la Cruz | M9: IG | O9: Pendiente | P9: Instagram | Q9: 2000 | R9: 0 | S9: 0 | T9: =Q9+R9+S9 -> 2000 | U9: =VLOOKUP(G9,'1. Catálogo'!$A$4:$G$9,7,FALSE)+K9+S9 -> 800 | V9: =T9-U9 -> 1200 | W9: Banreservas | X9: Recibido | Y9: Bloqueado - Sin Dirección
A10: P0007 | B10: 24/01/2026 | C10: 07/02/2026 | E10: =C10-B10 -> 14 | F10: =IF(D10="",IF(TODAY()>C10,TODAY()-C10,0),IF(D10>C10,D10-C10,0)) -> 0 | G10: TS-NEG-ST | H10: T-shirt negro | I10: S | J10: Frente bordado | K10: 150 | L10: Luz Rosmeri Morrobel | M10: IG | O10: Pendiente | P10: Instagram | Q10: 1952 | R10: 0 | S10: 0 | T10: =Q10+R10+S10 -> 1952 | U10: =VLOOKUP(G10,'1. Catálogo'!$A$4:$G$9,7,FALSE)+K10+S10 -> 800 | V10: =T10-U10 -> 1152 | W10: BHD | X10: Recibido | Y10: Bloqueado - Sin Dirección
A11: P0008 | B11: 04/02/2026 | C11: 13/02/2026 | E11: =C11-B11 -> 9 | F11: =IF(D11="",IF(TODAY()>C11,TODAY()-C11,0),IF(D11>C11,D11-C11,0)) -> 0 | G11: TS-NEG-ST | H11: T-shirt negro + Abrigo negro | I11: XL | J11: Bordado en frente | K11: 150 | L11: Katherine Pantoja | M11: WS | O11: APTPRA San Pedro | P11: WhatsApp | Q11: 4400 | R11: 0 | S11: 0 | T11: =Q11+R11+S11 -> 4400 | U11: =VLOOKUP(G11,'1. Catálogo'!$A$4:$G$9,7,FALSE)+K11+S11 -> 800 | V11: =T11-U11 -> 3600 | W11: Banreservas | X11: Recibido | Y11: En Producción
A12: P0009 | B12: 19/01/2026 | C12: 03/02/2026 | E12: =C12-B12 -> 15 | F12: =IF(D12="",IF(TODAY()>C12,TODAY()-C12,0),IF(D12>C12,D12-C12,0)) -> 0 | G12: TS-NEG-ST | H12: T-shirt negro | I12: XL | J12: Frente bordado | K12: 150 | L12: Santa Ferrreira Dolores | M12: IG | O12: Pendiente | P12: Instagram | Q12: 2000 | R12: 0 | S12: 0 | T12: =Q12+R12+S12 -> 2000 | U12: =VLOOKUP(G12,'1. Catálogo'!$A$4:$G$9,7,FALSE)+K12+S12 -> 800 | V12: =T12-U12 -> 1200 | W12: Banreservas | X12: Recibido | Y12: Bloqueado - Sin Dirección

Sheet 3. Dashboard
A1: DASHBOARD EJECUTIVO
B3: INDICADORES CLAVE | E3: VENTAS POR CANAL
B4: Total Pedidos: | C4: =COUNTA('2. Pedidos'!A4:A1000) -> 9 | E4: WhatsApp | F4: =SUMIF('2. Pedidos'!P:P,"WhatsApp",'2. Pedidos'!T:T) -> 17950
B5: Ventas Totales: | C5: =SUM('2. Pedidos'!T4:T1000) -> 23902 | E5: Instagram | F5: =SUMIF('2. Pedidos'!P:P,"Instagram",'2. Pedidos'!T:T) -> 5952
B6: Costos Totales: | C6: =SUM('2. Pedidos'!U4:U1000) -> 10400 | E6: Facebook | F6: =SUMIF('2. Pedidos'!P:P,"Facebook",'2. Pedidos'!T:T) -> 0
B7: Ganancia Neta: | C7: =SUM('2. Pedidos'!V4:V1000) -> 13502 | E7: Referido | F7: =SUMIF('2. Pedidos'!P:P,"Referido",'2. Pedidos'!T:T) -> 0
B8: Margen Promedio: | C8: =AVERAGE('2. Pedidos'!V4:V1000/'2. Pedidos'!T4:T1000) -> 0.37837838
B9: Ticket Promedio: | C9: =AVERAGE('2. Pedidos'!T4:T1000) -> 2655.7778 | E9: TOP PRODUCTOS
E10: TS-NEG-ST | F10: =COUNTIF('2. Pedidos'!G:G,"TS-NEG-ST") -> 6
E11: HD-NEG-ST | F11: =COUNTIF('2. Pedidos'!G:G,"HD-NEG-ST") -> 2
B12: ALERTAS OPERATIVAS | E12: TS-BL-OS | F12: =COUNTIF('2. Pedidos'!G:G,"TS-BL-OS") -> 1
B13: 🔴 Pedidos Atrasados: | C13: =COUNTIF('2. Pedidos'!F4:F1000,">0") -> 0
B14: ⚠️ Sin Dirección: | C14: =COUNTIF('2. Pedidos'!O4:O1000,"PENDIENTE") -> 4
B15: 📦 En Producción: | C15: =COUNTIF('2. Pedidos'!Y4:Y1000,"En Producción") -> 5
B16: ✅ Entregados: | C16: =COUNTIF('2. Pedidos'!Y4:Y1000,"Entregado") -> 0
B17: 💰 Pagos Pendientes: | C17: =COUNTIF('2. Pedidos'!X4:X1000,"Pendiente") -> 0

Sheet 4. Clientes
A1: BASE DE DATOS DE CLIENTES
A3: ID Cliente | B3: Nombre Completo | C3: Teléfono | D3: Email | E3: Dirección Principal | F3: Canal Preferido | G3: Total Pedidos | H3: Total Comprado | I3: Último Pedido | J3: Tipo Cliente
A4: C001 | B4: Ana | C4: 809-555-0101 | D4: ana@email.com | E4: Vimenpaq | F4: WhatsApp | G4: =COUNTIF('2. Pedidos'!L:L,B4) -> 1 | H4: =SUMIF('2. Pedidos'!L:L,B4,'2. Pedidos'!T:T) -> 3150 | I4: =_xludf.MAXIFS('2. Pedidos'!B:B,'2. Pedidos'!L:L,B4) -> #NAME? | J4: =IF(G4>=5,"VIP",IF(G4>=3,"Frecuente","Nuevo")) -> Nuevo

Sheet 5. Inventario
A1: CONTROL DE INVENTARIO
A3: SKU | B3: Producto | C3: Stock Actual | D3: Stock Mínimo | E3: Estado | F3: En Pedidos | G3: Stock Disponible | H3: Reorden Necesario
A4: TS-BL-OS | B4: T-shirt Blanco Oversize | C4: 15 | D4: 10 | E4: =IF(C4<D4,"⚠️ BAJO",IF(C4<D4*2,"✅ OK","📦 EXCESO")) -> ✅ OK | F4: =COUNTIF('2. Pedidos'!G:G,A4) -> 1 | G4: =C4-F4 -> 14 | H4: =IF(G4<D4,"SÍ","NO") -> NO
A5: TS-NEG-ST | B5: T-shirt Negro Standard | C5: 8 | D5: 10 | E5: =IF(C5<D5,"⚠️ BAJO",IF(C5<D5*2,"✅ OK","📦 EXCESO")) -> ⚠️ BAJO | F5: =COUNTIF('2. Pedidos'!G:G,A5) -> 6 | G5: =C5-F5 -> 2 | H5: =IF(G5<D5,"SÍ","NO") -> SÍ
A6: HD-NEG-ST | B6: Hoodie Negro Standard | C6: 5 | D6: 8 | E6: =IF(C6<D6,"⚠️ BAJO",IF(C6<D6*2,"✅ OK","📦 EXCESO")) -> ⚠️ BAJO | F6: =COUNTIF('2. Pedidos'!G:G,A6) -> 2 | G6: =C6-F6 -> 3 | H6: =IF(G6<D6,"SÍ","NO") -> SÍ

Sheet 6. Finanzas
A1: ANÁLISIS FINANCIERO DETALLADO
B3: RESUMEN ENERO 2026
B4: Ingresos Brutos: | C4: =SUMIFS('2. Pedidos'!T:T,'2. Pedidos'!B:B,">="&DATE(2026,1,1),'2. Pedidos'!B:B,"<"&DATE(2026,2,1)) -> 0
B5: Costos Totales: | C5: =SUMIFS('2. Pedidos'!U:U,'2. Pedidos'!B:B,">="&DATE(2026,1,1),'2. Pedidos'!B:B,"<"&DATE(2026,2,1)) -> 0
B6: Ganancia Neta: | C6: =C4-C5 -> 0
B7: Margen Neto: | C7: =C6/C4 -> #DIV/0!
B8: Pedidos del Mes: | C8: =COUNTIFS('2. Pedidos'!B:B,">="&DATE(2026,1,1),'2. Pedidos'!B:B,"<"&DATE(2026,2,1)) -> 0
B9: Ticket Promedio: | C9: =C4/C8 -> #DIV/0!
B12: ANÁLISIS POR BANCO | C12: Total Vendido | D12: Cantidad
B13: Popular | C13: =SUMIF('2. Pedidos'!W:W,"Popular",'2. Pedidos'!T:T) -> 7850 | D13: =COUNTIF('2. Pedidos'!W:W,"Popular") -> 3
B14: Banreservas | C14: =SUMIF('2. Pedidos'!W:W,"Banreservas",'2. Pedidos'!T:T) -> 14100 | D14: =COUNTIF('2. Pedidos'!W:W,"Banreservas") -> 5
B15: BHD | C15: =SUMIF('2. Pedidos'!W:W,"BHD",'2. Pedidos'!T:T) -> 1952 | D15: =COUNTIF('2. Pedidos'!W:W,"BHD") -> 1
B16: Efectivo | C16: =SUMIF('2. Pedidos'!W:W,"Efectivo",'2. Pedidos'!T:T) -> 0 | D16: =COUNTIF('2. Pedidos'!W:W,"Efectivo") -> 0

Sheet 7. Instrucciones
A1: GUÍA DE USO DEL SISTEMA
A3: 📋 INSTRUCCIONES DE USO 1. CATÁLOGO DE PRODUCTOS: - Actualiza precios y costos reales de tus productos - Añade nuevos productos según sea necesario - El sistema calculará automáticamente márgenes 2. REGISTRO DE PEDIDOS: - Usa las listas desplegables para evitar errores - El sistema calcula automáticamente costos y ganancias - Las fechas se validan automáticamente - Colores indican el estado: 🟢 Verde = Entregado 🟡 Amarillo = En producción 🔴 Rojo = Bloqueado o atrasado 3. DASHBOARD: - Actualización automática de todas las métricas - Revisa diariamente las alertas operativas - Identifica productos más vendidos 4. CLIENTES: - Se actualiza automáticamente con cada pedido - Clasifica clientes por frecuencia de compra - Identifica a tus mejores clientes (VIP) 5. INVENTARIO: - Actualiza stock manualmente después de producción - El sistema te alertará cuando esté bajo - Planifica reabastecimiento según demanda 6. FINANZAS: - Análisis mensual automático - Compara diferentes períodos - Identifica tendencias de ventas ⚠️ IMPORTANTE: - NO elimines las filas de encabezados - NO modifiques las fórmulas a menos que sepas lo que haces - Haz backup semanal del archivo - Completa TODOS los campos obligatorios 🎯 CAMPOS OBLIGATORIOS EN PEDIDOS: ✓ SKU del producto (debe existir en catálogo) ✓ Fecha de pago ✓ Fecha compromiso de envío ✓ Cliente (nombre completo) ✓ Teléfono ✓ Dirección de envío ✓ Banco/método de pago ✓ Estatus de pago ✓ Estatus de producción 💡 TIPS PARA MAXIMIZAR GANANCIAS: - Completa los costos reales en el catálogo - Revisa los márgenes por producto - Identifica productos de bajo margen - Optimiza tiempos de producción - Reduce pedidos bloqueados (sin dirección)
